tasksched/__init__.py
tasksched/parser.py
tasksched/project.py
tasksched/tasksched.py
tasksched/utils.py
tasksched/workplan.py
tasksched/workplan_html.py
tasksched/workplan_text.py
tasksched/data/css/dark.css
tasksched/data/css/light.css
tasksched/data/html/basic.html
tests/__init__.py
tests/test_project.py
tests/test_tasksched.py
tests/test_utils.py
tests/test_workplan.py
tests/test_workplan_html.py
tests/test_workplan_text.py
tests/utils.py
tasksched-0.5.0.dist-info/LICENSE.txt
tasksched-0.5.0.dist-info/METADATA
tasksched-0.5.0.dist-info/WHEEL
tasksched-0.5.0.dist-info/entry_points.txt
tasksched-0.5.0.dist-info/top_level.txt
tasksched-0.5.0.dist-info/RECORD
