Metadata-Version: 2.1
Name: tasksched
Version: 0.5.0
Summary: Task scheduler with automatic resource leveling.
Home-page: https://github.com/tasksched/tasksched
Author: Sébastien Helleu
Author-email: flashcode@flashtux.org
License: GPL3
Keywords: task scheduler planning automatic resource leveling
Platform: UNKNOWN
Classifier: Development Status :: 4 - Beta
Classifier: Environment :: Console
Classifier: Intended Audience :: End Users/Desktop
Classifier: License :: OSI Approved :: GNU General Public License v3 or later (GPLv3+)
Classifier: Operating System :: OS Independent
Classifier: Programming Language :: Python
Classifier: Programming Language :: Python :: 3
Classifier: Topic :: Office/Business
Classifier: Topic :: Office/Business :: Scheduling
Requires-Dist: holidays
Requires-Dist: jinja2
Requires-Dist: pyyaml
